pyusuggest/__init__.py
pyusuggest/exceptions.py
pyusuggest/ubersuggest.py
pyusuggest-1.0.5.dist-info/LICENSE.txt
pyusuggest-1.0.5.dist-info/METADATA
pyusuggest-1.0.5.dist-info/WHEEL
pyusuggest-1.0.5.dist-info/top_level.txt
pyusuggest-1.0.5.dist-info/RECORD
