Metadata-Version: 2.1
Name: pyusuggest
Version: 1.0.5
Summary: API to integrate Ubersuggest with Python
Home-page: https://github.com/Olegario96/pyusuggest
Author: Gustavo Olegario
Author-email: gustavo-olegario@hotmail.com
License: BEER-WARE
Platform: UNKNOWN
Requires-Dist: atomicwrites (==1.2.1)
Requires-Dist: attrs (==18.2.0)
Requires-Dist: certifi (==2018.11.29)
Requires-Dist: chardet (==3.0.4)
Requires-Dist: idna (==2.8)
Requires-Dist: more-itertools (==4.3.0)
Requires-Dist: pluggy (==0.8.0)
Requires-Dist: py (==1.7.0)
Requires-Dist: pytest (==4.0.2)
Requires-Dist: requests (==2.21.0)
Requires-Dist: six (==1.12.0)
Requires-Dist: urllib3 (==1.24.1)
